{
   "files": [    

{
         "name": "TrueMove-Game-001-VIP",
         "url": "https://sshsslvpn.000webhostapp.com/Game-001.ovpn"
      },


{
         "name": "TrueMove-Game-002-VIP",
         "url": "https://sshsslvpn.000webhostapp.com/Game-002.ovpn"
      },
{
         "name": "TrueMove-Game-003-VIP",
         "url": "https://sshsslvpn.000webhostapp.com/Game-003.ovpn"
      },

{
         "name": "TrueMove-Game-004-VIP",
         "url": "https://sshsslvpn.000webhostapp.com/Game-004.ovpn"
      },


      
{
         "name": "TrueMove-Game-005-VIP",
         "url": "https://sshsslvpn.000webhostapp.com/Game-005.ovpn"
      },

{
         "name": "Dtac-90DAYS-Game-001-VIP",
         "url": "https://sshsslvpn.000webhostapp.com/Game-001.ovpn"
      },


{
         "name": "Dtac-90DAYS-Game-002-VIP",
         "url": "https://sshsslvpn.000webhostapp.com/Game-002.ovpn"
      },
{
         "name": "Dtac-90DAYS-Game-003-VIP",
         "url": "https://sshsslvpn.000webhostapp.com/Game-003.ovpn"
      },

{
         "name": "Dtac-90DAYS-Game-004-VIP",
         "url": "https://sshsslvpn.000webhostapp.com/Game-004.ovpn"
      },


      
{
         "name": "Dtac-90DAYS-Game-005-VIP",
         "url": "https://sshsslvpn.000webhostapp.com/Game-005.ovpn"
      },

      
{
         "name": "Dtac-Line-Game-001-VIP",
         "url": "https://sshsslvpn.000webhostapp.com/Dtac-Line-001.ovpn"
      },

{
         "name": "Dtac-Line-Game-002-VIP",
         "url": "https://sshsslvpn.000webhostapp.com/Dtac-Line-002.ovpn"
      },


      
{
         "name": "Dtac-Line-Game-003-VIP",
         "url": "https://sshsslvpn.000webhostapp.com/Dtac-Line-003.ovpn"
      },

      
{
         "name": "Dtac-Line-Game-004-VIP",
         "url": "https://sshsslvpn.000webhostapp.com/Dtac-Line-004.ovpn"
      },

{
         "name": "Dtac-Line-Game-005-VIP",
         "url": "https://sshsslvpn.000webhostapp.com/Dtac-Line-005.ovpn"
      },

{
         "name": "Ais-Play-Game-001-VIP",
         "url": "https://sshsslvpn.000webhostapp.com/Ais-001.ovpn"
      },


      
{
         "name": "Ais-Play-Game-002-VIP",
         "url": "https://sshsslvpn.000webhostapp.com/Ais-002.ovpn"
      },

      
{
         "name": "Ais-Play-Game-003-VIP",
         "url": "https://sshsslvpn.000webhostapp.com/Ais-003.ovpn"
      },


{
         "name": "Ais-Play-Game-004-VIP",
         "url": "https://sshsslvpn.000webhostapp.com/Ais-004.ovpn"
      },

      
{
         "name": "Ais-Play-Game-005-VIP",
         "url": "https://sshsslvpn.000webhostapp.com/Ais-005.ovpn"
      },

{
         "name": "TrueMove-Game-006-VIP",
         "url": "https://sshsslvpn.000webhostapp.com/Game-006.ovpn"
      },


{
         "name": "TrueMove-Game-007-VIP",
         "url": "https://sshsslvpn.000webhostapp.com/Game-007.ovpn"
      },
{
         "name": "TrueMove-Game-008-VIP",
         "url": "https://sshsslvpn.000webhostapp.com/Game-008.ovpn"
      },

{
         "name": "TrueMove-Game-009-VIP",
         "url": "https://sshsslvpn.000webhostapp.com/Game-009.ovpn"
      },


      
{
         "name": "TrueMove-Game-010-VIP",
         "url": "https://sshsslvpn.000webhostapp.com/Game-010.ovpn"
      },

{
         "name": "Dtac-90DAYS-Game-006-VIP",
         "url": "https://sshsslvpn.000webhostapp.com/Game-006.ovpn"
      },


{
         "name": "Dtac-90DAYS-Game-007-VIP",
         "url": "https://sshsslvpn.000webhostapp.com/Game-007.ovpn"
      },
{
         "name": "Dtac-90DAYS-Game-008-VIP",
         "url": "https://sshsslvpn.000webhostapp.com/Game-008.ovpn"
      },

{
         "name": "Dtac-90DAYS-Game-009-VIP",
         "url": "https://sshsslvpn.000webhostapp.com/Game-009.ovpn"
      },


      
{
         "name": "Dtac-90DAYS-Game-010-VIP",
         "url": "https://sshsslvpn.000webhostapp.com/Game-010.ovpn"
      },

{
         "name": "Dtac-HWork-Game-001-VIP",
         "url": "https://sshsslvpn.000webhostapp.com/Dtac-Work-001.ovpn"
      },


{
         "name": "Dtac-HWork-Game-002-VIP",
         "url": "https://sshsslvpn.000webhostapp.com/Dtac-Work-002.ovpn"
      },
{
         "name": "Dtac-HWork-Game-003-VIP",
         "url": "https://sshsslvpn.000webhostapp.com/Dtac-Work-003.ovpn"
      },

{
         "name": "Dtac-HWork-Game-004-VIP",
         "url": "https://sshsslvpn.000webhostapp.com/Dtac-Work-004.ovpn"
      },


      
{
         "name": "Dtac-HWork-Game-005-VIP",
         "url": "https://sshsslvpn.000webhostapp.com/Dtac-Work-005.ovpn"
      }


   ],
"message":"Update 3 September 2021\n•All New Servers\n•Version: 1\n\n•Config By:💔အပြုံးတစ်ပွင့်ကြောင့် ကြွေခဲ့တဲ့အသည်း💔 ",
   "title":"Add Dtac HWork" ,
   "version": 1
}
